Transmitter.sv
module Transmitter(input logic EN, CLK, Reset,
                   input logic [7:0] DataIN,
                   output logic tx);

    logic [7:0] databuffer, count;
    enum logic [1:0] {IDLE, START, TRANSMIT, STOP} state;


    always_ff @(posedge CLK) begin
        
        if (Reset) begin
            state <= IDLE; 
        end

        case(state)
            IDLE: begin
                tx <= 1;
                if (EN) begin
                    state <= START;
                    tx <= 0;
                end
            end 
            START: begin
                tx <= DataIN[7];
                databuffer <= DataIN << 1;
                state <= TRANSMIT;
                count <= 1;
            end
            TRANSMIT: begin
                tx <= databuffer[7];
                databuffer <= databuffer << 1;
                count <= count + 1;
                if (count == 8) begin
                    state <= STOP;
                    tx <= 1;
                    state <= IDLE;
                end
            end
            default: begin
                
            end
        endcase
    end
endmodule

Transmitter_tb.sv
module Transmitter_tb;
    logic CLK, EN, Reset,tx;
    logic [7:0] DataIN;

    Transmitter Tx(
        .EN(EN), 
        .CLK(CLK), 
        .Reset(Reset),
        .DataIN(DataIN),
        .tx(tx)
    );

    always begin
        #1 CLK = ~CLK;
    end

    initial begin
        CLK = 0;
        EN = 0;
        Reset = 1;
        DataIN = 8'b11110000;
        #5;
        Reset=0;
        EN = 1;
        #100;
        
        $finish;
    end

    
    initial begin
        $dumpfile("Transmitter.vcd");
        $dumpvars(0,Transmitter_tb);
    end


endmodule

Transmitter.vcd
$version Generated by VerilatedVcd $end
$timescale 1ps $end
 $scope module TOP $end
  $scope module Transmitter_tb $end
   $var wire 1 ' CLK $end
   $var wire 1 ( EN $end
   $var wire 1 ) Reset $end
   $var wire 1 # tx $end
   $var wire 8 * DataIN [7:0] $end
   $scope module Tx $end
    $var wire 1 ( EN $end
    $var wire 1 ' CLK $end
    $var wire 1 ) Reset $end
    $var wire 8 * DataIN [7:0] $end
    $var wire 1 # tx $end
    $var wire 8 $ databuffer [7:0] $end
    $var wire 8 % count [7:0] $end
    $var wire 2 & state [1:0] $end
   $upscope $end
  $upscope $end
 $upscope $end
$enddefinitions $end


#0
0#
b00000000 $
b00000000 %
b00 &
0'
0(
1)
b11110000 *
#1
1#
1'
#2
0'
#3
1'
#4
0'
#5
0#
b01 &
1'
1(
0)
#6
0'
#7
1#
b11100000 $
b00000001 %
b10 &
1'
#8
0'
#9
b11000000 $
b00000010 %
1'
#10
0'
#11
b10000000 $
b00000011 %
1'
#12
0'
#13
b00000000 $
b00000100 %
1'
#14
0'
#15
0#
b00000101 %
1'
#16
0'
#17
b00000110 %
1'
#18
0'
#19
b00000111 %
1'
#20
0'
#21
b00001000 %
1'
#22
0'
#23
1#
b00001001 %
b00 &
1'
#24
0'
#25
0#
b01 &
1'
#26
0'
#27
1#
b11100000 $
b00000001 %
b10 &
1'
#28
0'
#29
b11000000 $
b00000010 %
1'
#30
0'
#31
b10000000 $
b00000011 %
1'
#32
0'
#33
b00000000 $
b00000100 %
1'
#34
0'
#35
0#
b00000101 %
1'
#36
0'
#37
b00000110 %
1'
#38
0'
#39
b00000111 %
1'
#40
0'
#41
b00001000 %
1'
#42
0'
#43
1#
b00001001 %
b00 &
1'
#44
0'
#45
0#
b01 &
1'
#46
0'
#47
1#
b11100000 $
b00000001 %
b10 &
1'
#48
0'
#49
b11000000 $
b00000010 %
1'
#50
0'
#51
b10000000 $
b00000011 %
1'
#52
0'
#53
b00000000 $
b00000100 %
1'
#54
0'
#55
0#
b00000101 %
1'
#56
0'
#57
b00000110 %
1'
#58
0'
#59
b00000111 %
1'
#60
0'
#61
b00001000 %
1'
#62
0'
#63
1#
b00001001 %
b00 &
1'
#64
0'
#65
0#
b01 &
1'
#66
0'
#67
1#
b11100000 $
b00000001 %
b10 &
1'
#68
0'
#69
b11000000 $
b00000010 %
1'
#70
0'
#71
b10000000 $
b00000011 %
1'
#72
0'
#73
b00000000 $
b00000100 %
1'
#74
0'
#75
0#
b00000101 %
1'
#76
0'
#77
b00000110 %
1'
#78
0'
#79
b00000111 %
1'
#80
0'
#81
b00001000 %
1'
#82
0'
#83
1#
b00001001 %
b00 &
1'
#84
0'
#85
0#
b01 &
1'
#86
0'
#87
1#
b11100000 $
b00000001 %
b10 &
1'
#88
0'
#89
b11000000 $
b00000010 %
1'
#90
0'
#91
b10000000 $
b00000011 %
1'
#92
0'
#93
b00000000 $
b00000100 %
1'
#94
0'
#95
0#
b00000101 %
1'
#96
0'
#97
b00000110 %
1'
#98
0'
#99
b00000111 %
1'
#100
0'
#101
b00001000 %
1'
#102
0'
#103
1#
b00001001 %
b00 &
1'
#104
0'
#105
0#
b01 &
1'
