Receiver.sv
module Receiver (
    input  logic BaudTick, CLK, Reset,
    input  logic rx, 
    input  logic ParityType, // <-- 0 = even, 1 = odd
    output logic [7:0] DataOUT,
    output logic ParityError
);

    enum logic [2:0] {IDLE, RECEIVE, PARITY, STOP} state;
    logic [7:0] databuffer;
    logic [2:0] count;
    logic parity_bit;
    logic computed_parity;

    always_ff @(posedge CLK) begin
        if (Reset) begin
            state <= IDLE;
            ParityError <= 0;
        end
        else if (BaudTick) begin
            case (state)
                IDLE: begin
                    databuffer <= 0;
                    DataOUT <= 0;
                    ParityError <= 0;
                    if (rx == 0) begin
                        state <= RECEIVE;
                        count <= 7;
                    end
                end

                RECEIVE: begin
                    databuffer[count] <= rx;
                    if (count == 0) begin
                        state <= PARITY;
                    end
                    else begin
                        count <= count - 1;
                    end
                end

                PARITY: begin
                    parity_bit <= rx; 
                    // compute parity depending on type
                    computed_parity = (ParityType) ? ~(^databuffer) : ^databuffer;
                    ParityError <= (computed_parity != parity_bit);
                    state <= STOP;
                end

                STOP: begin
                    DataOUT <= databuffer;
                    state <= IDLE;
                end

                default: state <= IDLE;
            endcase
        end
    end
endmodule

Transmitter.sv
module Transmitter(
    input  logic BaudTick, EN, CLK, Reset,
    input  logic [7:0] DataIN,
    input  logic ParityType, // <-- 0 = even, 1 = odd
    output logic tx
);
    logic [7:0] databuffer, count;
    logic parity_bit;
    enum logic [2:0] {IDLE, START, TRANSMIT, PARITY, STOP} state;

    always_ff @(posedge CLK) begin
        if (Reset) begin
            state <= IDLE; 
        end
        else if (BaudTick) begin
            case(state)
                IDLE: begin
                    tx <= 1;
                    if (EN) begin
                        state <= START;
                        tx <= 0;
                    end
                end 
                START: begin
                    tx <= DataIN[7];
                    databuffer <= DataIN << 1;
                    // compute parity depending on type
                    parity_bit <= (ParityType) ? ~(^DataIN) : ^DataIN;
                    state <= TRANSMIT;
                    count <= 1;
                end
                TRANSMIT: begin
                    tx <= databuffer[7];
                    databuffer <= databuffer << 1;
                    count <= count + 1;
                    if (count == 8) begin
                        state <= PARITY;
                    end
                end
                PARITY: begin
                    tx <= parity_bit; // send parity bit
                    state <= STOP;
                end
                STOP: begin
                    tx <= 1; // stop bit
                    state <= IDLE;
                end
                default: state <= IDLE;
            endcase
        end
    end
endmodule

BaudGenerator.sv
module BaudGenerator (
    input  logic CLK,     
    input  logic Reset,   
    output logic BaudTick
);

    logic [12:0] MAX_COUNT = 13'd16;

    logic [12:0] count; // 13 bits are enough for 5208

    always_ff @(posedge CLK) begin
        if (Reset) begin
            count     <= 13'd0;
            BaudTick  <= 1'b0;
        end else begin
            if (count == MAX_COUNT - 1) begin
                count     <= 13'd0;
                BaudTick  <= 1'b1;  
            end 
            else begin
                count     <= count + 1;
                BaudTick  <= 1'b0; 
            end
        end
    end
endmodule

UART.sv
module UART (
    input  logic CLK, EN, Reset,
    input  logic [7:0] DataIN,
    input  logic ParityType,       // 0 = even, 1 = odd
    output logic [7:0] DataOUT,
    output logic ParityError
);

    logic tx = 1, BaudTick;

    BaudGenerator BaudGen(
        .CLK(CLK),     
        .Reset(Reset),   
        .BaudTick(BaudTick)
    );

    Transmitter TX(
        .CLK(CLK),
        .BaudTick(BaudTick),
        .Reset(Reset),
        .EN(EN),
        .DataIN(DataIN),
        .ParityType(ParityType), // <-- connected
        .tx(tx)
    );

    Receiver RX(
        .CLK(CLK),
        .BaudTick(BaudTick),
        .Reset(Reset),
        .rx(tx),
        .ParityType(ParityType),  // <-- connected
        .DataOUT(DataOUT),
        .ParityError(ParityError)
    );    

endmodule

UART_TestBench.sv
module UART_TestBench;
    logic CLK, EN, Reset;
    logic [7:0] DataIN, DataOUT;
    logic ParityType;
    logic ParityError;

    UART DUT(
        .CLK(CLK),
        .EN(EN),
        .Reset(Reset),
        .DataIN(DataIN),
        .DataOUT(DataOUT),
        .ParityType(ParityType),
        .ParityError(ParityError)
    );

    // Clock generation (1 time unit period)
    always #1 CLK = ~CLK;

    // Main stimulus
    initial begin
        CLK = 0;
        Reset = 1;
        EN = 0;
        DataIN = 8'h00;
        ParityType = 0;

        #5 Reset = 0;

        // Test 1: Even parity, 0xAA
        ParityType = 0;
        DataIN = 8'hAA;
        EN = 1;
        #400;

        // Test 2: Odd parity, 0x55
        ParityType = 1;
        DataIN = 8'h55;
        EN = 1;
        #400;

        // Test 3: Even parity, 0xF0
        ParityType = 0;
        DataIN = 8'hF0;
        EN = 1;
        #400;

        // Test 4: Odd parity, 0x0F
        ParityType = 1;
        DataIN = 8'h0F;
        EN = 1;
        #400;

        // Test 5: Even parity, 0xEA
        ParityType = 0;
        DataIN = 8'hEA;
        EN = 1;
        #400;

        // Test 6: Odd parity, 0xEA
        ParityType = 1;
        DataIN = 8'hEA;
        EN = 1;
        #400;

        $finish;
    end

    // VCD dump for GTKWave
    initial begin
        $dumpfile("UART.vcd");
        $dumpvars(0, UART_TestBench);
    end
endmodule

UART.vcd
$version Generated by VerilatedVcd $end
$timescale 1ps $end
 $scope module TOP $end
  $scope module UART_TestBench $end
   $var wire 1 1 CLK $end
   $var wire 1 2 EN $end
   $var wire 1 3 Reset $end
   $var wire 8 4 DataIN [7:0] $end
   $var wire 8 # DataOUT [7:0] $end
   $var wire 1 5 ParityType $end
   $var wire 1 $ ParityError $end
   $scope module DUT $end
    $var wire 1 1 CLK $end
    $var wire 1 2 EN $end
    $var wire 1 3 Reset $end
    $var wire 8 4 DataIN [7:0] $end
    $var wire 1 5 ParityType $end
    $var wire 8 # DataOUT [7:0] $end
    $var wire 1 $ ParityError $end
    $var wire 1 % tx $end
    $var wire 1 & BaudTick $end
    $scope module BaudGen $end
     $var wire 1 1 CLK $end
     $var wire 1 3 Reset $end
     $var wire 1 & BaudTick $end
     $var wire 13 6 MAX_COUNT [12:0] $end
     $var wire 13 ' count [12:0] $end
    $upscope $end
    $scope module RX $end
     $var wire 1 & BaudTick $end
     $var wire 1 1 CLK $end
     $var wire 1 3 Reset $end
     $var wire 1 % rx $end
     $var wire 1 5 ParityType $end
     $var wire 8 # DataOUT [7:0] $end
     $var wire 1 $ ParityError $end
     $var wire 3 ( state [2:0] $end
     $var wire 8 ) databuffer [7:0] $end
     $var wire 3 * count [2:0] $end
     $var wire 1 + parity_bit $end
     $var wire 1 , computed_parity $end
    $upscope $end
    $scope module TX $end
     $var wire 1 & BaudTick $end
     $var wire 1 2 EN $end
     $var wire 1 1 CLK $end
     $var wire 1 3 Reset $end
     $var wire 8 4 DataIN [7:0] $end
     $var wire 1 5 ParityType $end
     $var wire 1 % tx $end
     $var wire 8 - databuffer [7:0] $end
     $var wire 8 . count [7:0] $end
     $var wire 1 / parity_bit $end
     $var wire 3 0 state [2:0] $end
    $upscope $end
   $upscope $end
  $upscope $end
 $upscope $end
$enddefinitions $end


#0
b00000000 #
0$
1%
0&
b0000000000000 '
b000 (
b00000000 )
b000 *
0+
0,
b00000000 -
b00000000 .
0/
b000 0
01
02
13
b00000000 4
05
b0000000010000 6
#1
11
#2
01
#3
11
#4
01
#5
b0000000000001 '
11
12
03
b10101010 4
#6
01
#7
b0000000000010 '
11
#8
01
#9
b0000000000011 '
11
#10
01
#11
b0000000000100 '
11
#12
01
#13
b0000000000101 '
11
#14
01
#15
b0000000000110 '
11
#16
01
#17
b0000000000111 '
11
#18
01
#19
b0000000001000 '
11
#20
01
#21
b0000000001001 '
11
#22
01
#23
b0000000001010 '
11
#24
01
#25
b0000000001011 '
11
#26
01
#27
b0000000001100 '
11
#28
01
#29
b0000000001101 '
11
#30
01
#31
b0000000001110 '
11
#32
01
#33
b0000000001111 '
11
#34
01
#35
1&
b0000000000000 '
11
#36
01
#37
0%
0&
b0000000000001 '
b001 0
11
#38
01
#39
b0000000000010 '
11
#40
01
#41
b0000000000011 '
11
#42
01
#43
b0000000000100 '
11
#44
01
#45
b0000000000101 '
11
#46
01
#47
b0000000000110 '
11
#48
01
#49
b0000000000111 '
11
#50
01
#51
b0000000001000 '
11
#52
01
#53
b0000000001001 '
11
#54
01
#55
b0000000001010 '
11
#56
01
#57
b0000000001011 '
11
#58
01
#59
b0000000001100 '
11
#60
01
#61
b0000000001101 '
11
#62
01
#63
b0000000001110 '
11
#64
01
#65
b0000000001111 '
11
#66
01
#67
1&
b0000000000000 '
11
#68
01
#69
1%
0&
b0000000000001 '
b001 (
b111 *
b01010100 -
b00000001 .
b010 0
11
#70
01
#71
b0000000000010 '
11
#72
01
#73
b0000000000011 '
11
#74
01
#75
b0000000000100 '
11
#76
01
#77
b0000000000101 '
11
#78
01
#79
b0000000000110 '
11
#80
01
#81
b0000000000111 '
11
#82
01
#83
b0000000001000 '
11
#84
01
#85
b0000000001001 '
11
#86
01
#87
b0000000001010 '
11
#88
01
#89
b0000000001011 '
11
#90
01
#91
b0000000001100 '
11
#92
01
#93
b0000000001101 '
11
#94
01
#95
b0000000001110 '
11
#96
01
#97
b0000000001111 '
11
#98
01
#99
1&
b0000000000000 '
11
#100
01
#101
0%
0&
b0000000000001 '
b10000000 )
b110 *
b10101000 -
b00000010 .
11
#102
01
#103
b0000000000010 '
11
#104
01
#105
b0000000000011 '
11
#106
01
#107
b0000000000100 '
11
#108
01
#109
b0000000000101 '
11
#110
01
#111
b0000000000110 '
11
#112
01
#113
b0000000000111 '
11
#114
01
#115
b0000000001000 '
11
#116
01
#117
b0000000001001 '
11
#118
01
#119
b0000000001010 '
11
#120
01
#121
b0000000001011 '
11
#122
01
#123
b0000000001100 '
11
#124
01
#125
b0000000001101 '
11
#126
01
#127
b0000000001110 '
11
#128
01
#129
b0000000001111 '
11
#130
01
#131
1&
b0000000000000 '
11
#132
01
#133
1%
0&
b0000000000001 '
b101 *
b01010000 -
b00000011 .
11
#134
01
#135
b0000000000010 '
11
#136
01
#137
b0000000000011 '
11
#138
01
#139
b0000000000100 '
11
#140
01
#141
b0000000000101 '
11
#142
01
#143
b0000000000110 '
11
#144
01
#145
b0000000000111 '
11
#146
01
#147
b0000000001000 '
11
#148
01
#149
b0000000001001 '
11
#150
01
#151
b0000000001010 '
11
#152
01
#153
b0000000001011 '
11
#154
01
#155
b0000000001100 '
11
#156
01
#157
b0000000001101 '
11
#158
01
#159
b0000000001110 '
11
#160
01
#161
b0000000001111 '
11
#162
01
#163
1&
b0000000000000 '
11
#164
01
#165
0%
0&
b0000000000001 '
b10100000 )
b100 *
b10100000 -
b00000100 .
11
#166
01
#167
b0000000000010 '
11
#168
01
#169
b0000000000011 '
11
#170
01
#171
b0000000000100 '
11
#172
01
#173
b0000000000101 '
11
#174
01
#175
b0000000000110 '
11
#176
01
#177
b0000000000111 '
11
#178
01
#179
b0000000001000 '
11
#180
01
#181
b0000000001001 '
11
#182
01
#183
b0000000001010 '
11
#184
01
#185
b0000000001011 '
11
#186
01
#187
b0000000001100 '
11
#188
01
#189
b0000000001101 '
11
#190
01
#191
b0000000001110 '
11
#192
01
#193
b0000000001111 '
11
#194
01
#195
1&
b0000000000000 '
11
#196
01
#197
1%
0&
b0000000000001 '
b011 *
b01000000 -
b00000101 .
11
#198
01
#199
b0000000000010 '
11
#200
01
#201
b0000000000011 '
11
#202
01
#203
b0000000000100 '
11
#204
01
#205
b0000000000101 '
11
#206
01
#207
b0000000000110 '
11
#208
01
#209
b0000000000111 '
11
#210
01
#211
b0000000001000 '
11
#212
01
#213
b0000000001001 '
11
#214
01
#215
b0000000001010 '
11
#216
01
#217
b0000000001011 '
11
#218
01
#219
b0000000001100 '
11
#220
01
#221
b0000000001101 '
11
#222
01
#223
b0000000001110 '
11
#224
01
#225
b0000000001111 '
11
#226
01
#227
1&
b0000000000000 '
11
#228
01
#229
0%
0&
b0000000000001 '
b10101000 )
b010 *
b10000000 -
b00000110 .
11
#230
01
#231
b0000000000010 '
11
#232
01
#233
b0000000000011 '
11
#234
01
#235
b0000000000100 '
11
#236
01
#237
b0000000000101 '
11
#238
01
#239
b0000000000110 '
11
#240
01
#241
b0000000000111 '
11
#242
01
#243
b0000000001000 '
11
#244
01
#245
b0000000001001 '
11
#246
01
#247
b0000000001010 '
11
#248
01
#249
b0000000001011 '
11
#250
01
#251
b0000000001100 '
11
#252
01
#253
b0000000001101 '
11
#254
01
#255
b0000000001110 '
11
#256
01
#257
b0000000001111 '
11
#258
01
#259
1&
b0000000000000 '
11
#260
01
#261
1%
0&
b0000000000001 '
b001 *
b00000000 -
b00000111 .
11
#262
01
#263
b0000000000010 '
11
#264
01
#265
b0000000000011 '
11
#266
01
#267
b0000000000100 '
11
#268
01
#269
b0000000000101 '
11
#270
01
#271
b0000000000110 '
11
#272
01
#273
b0000000000111 '
11
#274
01
#275
b0000000001000 '
11
#276
01
#277
b0000000001001 '
11
#278
01
#279
b0000000001010 '
11
#280
01
#281
b0000000001011 '
11
#282
01
#283
b0000000001100 '
11
#284
01
#285
b0000000001101 '
11
#286
01
#287
b0000000001110 '
11
#288
01
#289
b0000000001111 '
11
#290
01
#291
1&
b0000000000000 '
11
#292
01
#293
0%
0&
b0000000000001 '
b10101010 )
b000 *
b00001000 .
11
#294
01
#295
b0000000000010 '
11
#296
01
#297
b0000000000011 '
11
#298
01
#299
b0000000000100 '
11
#300
01
#301
b0000000000101 '
11
#302
01
#303
b0000000000110 '
11
#304
01
#305
b0000000000111 '
11
#306
01
#307
b0000000001000 '
11
#308
01
#309
b0000000001001 '
11
#310
01
#311
b0000000001010 '
11
#312
01
#313
b0000000001011 '
11
#314
01
#315
b0000000001100 '
11
#316
01
#317
b0000000001101 '
11
#318
01
#319
b0000000001110 '
11
#320
01
#321
b0000000001111 '
11
#322
01
#323
1&
b0000000000000 '
11
#324
01
#325
0&
b0000000000001 '
b010 (
b00001001 .
b011 0
11
#326
01
#327
b0000000000010 '
11
#328
01
#329
b0000000000011 '
11
#330
01
#331
b0000000000100 '
11
#332
01
#333
b0000000000101 '
11
#334
01
#335
b0000000000110 '
11
#336
01
#337
b0000000000111 '
11
#338
01
#339
b0000000001000 '
11
#340
01
#341
b0000000001001 '
11
#342
01
#343
b0000000001010 '
11
#344
01
#345
b0000000001011 '
11
#346
01
#347
b0000000001100 '
11
#348
01
#349
b0000000001101 '
11
#350
01
#351
b0000000001110 '
11
#352
01
#353
b0000000001111 '
11
#354
01
#355
1&
b0000000000000 '
11
#356
01
#357
0&
b0000000000001 '
b011 (
b100 0
11
#358
01
#359
b0000000000010 '
11
#360
01
#361
b0000000000011 '
11
#362
01
#363
b0000000000100 '
11
#364
01
#365
b0000000000101 '
11
#366
01
#367
b0000000000110 '
11
#368
01
#369
b0000000000111 '
11
#370
01
#371
b0000000001000 '
11
#372
01
#373
b0000000001001 '
11
#374
01
#375
b0000000001010 '
11
#376
01
#377
b0000000001011 '
11
#378
01
#379
b0000000001100 '
11
#380
01
#381
b0000000001101 '
11
#382
01
#383
b0000000001110 '
11
#384
01
#385
b0000000001111 '
11
#386
01
#387
1&
b0000000000000 '
11
#388
01
#389
b10101010 #
1%
0&
b0000000000001 '
b000 (
b000 0
11
#390
01
#391
b0000000000010 '
11
#392
01
#393
b0000000000011 '
11
#394
01
#395
b0000000000100 '
11
#396
01
#397
b0000000000101 '
11
#398
01
#399
b0000000000110 '
11
#400
01
#401
b0000000000111 '
11
#402
01
#403
b0000000001000 '
11
#404
01
#405
b0000000001001 '
11
b01010101 4
15
#406
01
#407
b0000000001010 '
11
#408
01
#409
b0000000001011 '
11
#410
01
#411
b0000000001100 '
11
#412
01
#413
b0000000001101 '
11
#414
01
#415
b0000000001110 '
11
#416
01
#417
b0000000001111 '
11
#418
01
#419
1&
b0000000000000 '
11
#420
01
#421
b00000000 #
0%
0&
b0000000000001 '
b00000000 )
b001 0
11
#422
01
#423
b0000000000010 '
11
#424
01
#425
b0000000000011 '
11
#426
01
#427
b0000000000100 '
11
#428
01
#429
b0000000000101 '
11
#430
01
#431
b0000000000110 '
11
#432
01
#433
b0000000000111 '
11
#434
01
#435
b0000000001000 '
11
#436
01
#437
b0000000001001 '
11
#438
01
#439
b0000000001010 '
11
#440
01
#441
b0000000001011 '
11
#442
01
#443
b0000000001100 '
11
#444
01
#445
b0000000001101 '
11
#446
01
#447
b0000000001110 '
11
#448
01
#449
b0000000001111 '
11
#450
01
#451
1&
b0000000000000 '
11
#452
01
#453
0&
b0000000000001 '
b001 (
b111 *
b10101010 -
b00000001 .
1/
b010 0
11
#454
01
#455
b0000000000010 '
11
#456
01
#457
b0000000000011 '
11
#458
01
#459
b0000000000100 '
11
#460
01
#461
b0000000000101 '
11
#462
01
#463
b0000000000110 '
11
#464
01
#465
b0000000000111 '
11
#466
01
#467
b0000000001000 '
11
#468
01
#469
b0000000001001 '
11
#470
01
#471
b0000000001010 '
11
#472
01
#473
b0000000001011 '
11
#474
01
#475
b0000000001100 '
11
#476
01
#477
b0000000001101 '
11
#478
01
#479
b0000000001110 '
11
#480
01
#481
b0000000001111 '
11
#482
01
#483
1&
b0000000000000 '
11
#484
01
#485
1%
0&
b0000000000001 '
b110 *
b01010100 -
b00000010 .
11
#486
01
#487
b0000000000010 '
11
#488
01
#489
b0000000000011 '
11
#490
01
#491
b0000000000100 '
11
#492
01
#493
b0000000000101 '
11
#494
01
#495
b0000000000110 '
11
#496
01
#497
b0000000000111 '
11
#498
01
#499
b0000000001000 '
11
#500
01
#501
b0000000001001 '
11
#502
01
#503
b0000000001010 '
11
#504
01
#505
b0000000001011 '
11
#506
01
#507
b0000000001100 '
11
#508
01
#509
b0000000001101 '
11
#510
01
#511
b0000000001110 '
11
#512
01
#513
b0000000001111 '
11
#514
01
#515
1&
b0000000000000 '
11
#516
01
#517
0%
0&
b0000000000001 '
b01000000 )
b101 *
b10101000 -
b00000011 .
11
#518
01
#519
b0000000000010 '
11
#520
01
#521
b0000000000011 '
11
#522
01
#523
b0000000000100 '
11
#524
01
#525
b0000000000101 '
11
#526
01
#527
b0000000000110 '
11
#528
01
#529
b0000000000111 '
11
#530
01
#531
b0000000001000 '
11
#532
01
#533
b0000000001001 '
11
#534
01
#535
b0000000001010 '
11
#536
01
#537
b0000000001011 '
11
#538
01
#539
b0000000001100 '
11
#540
01
#541
b0000000001101 '
11
#542
01
#543
b0000000001110 '
11
#544
01
#545
b0000000001111 '
11
#546
01
#547
1&
b0000000000000 '
11
#548
01
#549
1%
0&
b0000000000001 '
b100 *
b01010000 -
b00000100 .
11
#550
01
#551
b0000000000010 '
11
#552
01
#553
b0000000000011 '
11
#554
01
#555
b0000000000100 '
11
#556
01
#557
b0000000000101 '
11
#558
01
#559
b0000000000110 '
11
#560
01
#561
b0000000000111 '
11
#562
01
#563
b0000000001000 '
11
#564
01
#565
b0000000001001 '
11
#566
01
#567
b0000000001010 '
11
#568
01
#569
b0000000001011 '
11
#570
01
#571
b0000000001100 '
11
#572
01
#573
b0000000001101 '
11
#574
01
#575
b0000000001110 '
11
#576
01
#577
b0000000001111 '
11
#578
01
#579
1&
b0000000000000 '
11
#580
01
#581
0%
0&
b0000000000001 '
b01010000 )
b011 *
b10100000 -
b00000101 .
11
#582
01
#583
b0000000000010 '
11
#584
01
#585
b0000000000011 '
11
#586
01
#587
b0000000000100 '
11
#588
01
#589
b0000000000101 '
11
#590
01
#591
b0000000000110 '
11
#592
01
#593
b0000000000111 '
11
#594
01
#595
b0000000001000 '
11
#596
01
#597
b0000000001001 '
11
#598
01
#599
b0000000001010 '
11
#600
01
#601
b0000000001011 '
11
#602
01
#603
b0000000001100 '
11
#604
01
#605
b0000000001101 '
11
#606
01
#607
b0000000001110 '
11
#608
01
#609
b0000000001111 '
11
#610
01
#611
1&
b0000000000000 '
11
#612
01
#613
1%
0&
b0000000000001 '
b010 *
b01000000 -
b00000110 .
11
#614
01
#615
b0000000000010 '
11
#616
01
#617
b0000000000011 '
11
#618
01
#619
b0000000000100 '
11
#620
01
#621
b0000000000101 '
11
#622
01
#623
b0000000000110 '
11
#624
01
#625
b0000000000111 '
11
#626
01
#627
b0000000001000 '
11
#628
01
#629
b0000000001001 '
11
#630
01
#631
b0000000001010 '
11
#632
01
#633
b0000000001011 '
11
#634
01
#635
b0000000001100 '
11
#636
01
#637
b0000000001101 '
11
#638
01
#639
b0000000001110 '
11
#640
01
#641
b0000000001111 '
11
#642
01
#643
1&
b0000000000000 '
11
#644
01
#645
0%
0&
b0000000000001 '
b01010100 )
b001 *
b10000000 -
b00000111 .
11
#646
01
#647
b0000000000010 '
11
#648
01
#649
b0000000000011 '
11
#650
01
#651
b0000000000100 '
11
#652
01
#653
b0000000000101 '
11
#654
01
#655
b0000000000110 '
11
#656
01
#657
b0000000000111 '
11
#658
01
#659
b0000000001000 '
11
#660
01
#661
b0000000001001 '
11
#662
01
#663
b0000000001010 '
11
#664
01
#665
b0000000001011 '
11
#666
01
#667
b0000000001100 '
11
#668
01
#669
b0000000001101 '
11
#670
01
#671
b0000000001110 '
11
#672
01
#673
b0000000001111 '
11
#674
01
#675
1&
b0000000000000 '
11
#676
01
#677
1%
0&
b0000000000001 '
b000 *
b00000000 -
b00001000 .
11
#678
01
#679
b0000000000010 '
11
#680
01
#681
b0000000000011 '
11
#682
01
#683
b0000000000100 '
11
#684
01
#685
b0000000000101 '
11
#686
01
#687
b0000000000110 '
11
#688
01
#689
b0000000000111 '
11
#690
01
#691
b0000000001000 '
11
#692
01
#693
b0000000001001 '
11
#694
01
#695
b0000000001010 '
11
#696
01
#697
b0000000001011 '
11
#698
01
#699
b0000000001100 '
11
#700
01
#701
b0000000001101 '
11
#702
01
#703
b0000000001110 '
11
#704
01
#705
b0000000001111 '
11
#706
01
#707
1&
b0000000000000 '
11
#708
01
#709
0%
0&
b0000000000001 '
b010 (
b01010101 )
b00001001 .
b011 0
11
#710
01
#711
b0000000000010 '
11
#712
01
#713
b0000000000011 '
11
#714
01
#715
b0000000000100 '
11
#716
01
#717
b0000000000101 '
11
#718
01
#719
b0000000000110 '
11
#720
01
#721
b0000000000111 '
11
#722
01
#723
b0000000001000 '
11
#724
01
#725
b0000000001001 '
11
#726
01
#727
b0000000001010 '
11
#728
01
#729
b0000000001011 '
11
#730
01
#731
b0000000001100 '
11
#732
01
#733
b0000000001101 '
11
#734
01
#735
b0000000001110 '
11
#736
01
#737
b0000000001111 '
11
#738
01
#739
1&
b0000000000000 '
11
#740
01
#741
1$
1%
0&
b0000000000001 '
b011 (
1,
b100 0
11
#742
01
#743
b0000000000010 '
11
#744
01
#745
b0000000000011 '
11
#746
01
#747
b0000000000100 '
11
#748
01
#749
b0000000000101 '
11
#750
01
#751
b0000000000110 '
11
#752
01
#753
b0000000000111 '
11
#754
01
#755
b0000000001000 '
11
#756
01
#757
b0000000001001 '
11
#758
01
#759
b0000000001010 '
11
#760
01
#761
b0000000001011 '
11
#762
01
#763
b0000000001100 '
11
#764
01
#765
b0000000001101 '
11
#766
01
#767
b0000000001110 '
11
#768
01
#769
b0000000001111 '
11
#770
01
#771
1&
b0000000000000 '
11
#772
01
#773
b01010101 #
0&
b0000000000001 '
b000 (
b000 0
11
#774
01
#775
b0000000000010 '
11
#776
01
#777
b0000000000011 '
11
#778
01
#779
b0000000000100 '
11
#780
01
#781
b0000000000101 '
11
#782
01
#783
b0000000000110 '
11
#784
01
#785
b0000000000111 '
11
#786
01
#787
b0000000001000 '
11
#788
01
#789
b0000000001001 '
11
#790
01
#791
b0000000001010 '
11
#792
01
#793
b0000000001011 '
11
#794
01
#795
b0000000001100 '
11
#796
01
#797
b0000000001101 '
11
#798
01
#799
b0000000001110 '
11
#800
01
#801
b0000000001111 '
11
#802
01
#803
1&
b0000000000000 '
11
#804
01
#805
b00000000 #
0$
0%
0&
b0000000000001 '
b00000000 )
b001 0
11
b11110000 4
05
#806
01
#807
b0000000000010 '
11
#808
01
#809
b0000000000011 '
11
#810
01
#811
b0000000000100 '
11
#812
01
#813
b0000000000101 '
11
#814
01
#815
b0000000000110 '
11
#816
01
#817
b0000000000111 '
11
#818
01
#819
b0000000001000 '
11
#820
01
#821
b0000000001001 '
11
#822
01
#823
b0000000001010 '
11
#824
01
#825
b0000000001011 '
11
#826
01
#827
b0000000001100 '
11
#828
01
#829
b0000000001101 '
11
#830
01
#831
b0000000001110 '
11
#832
01
#833
b0000000001111 '
11
#834
01
#835
1&
b0000000000000 '
11
#836
01
#837
1%
0&
b0000000000001 '
b001 (
b111 *
b11100000 -
b00000001 .
0/
b010 0
11
#838
01
#839
b0000000000010 '
11
#840
01
#841
b0000000000011 '
11
#842
01
#843
b0000000000100 '
11
#844
01
#845
b0000000000101 '
11
#846
01
#847
b0000000000110 '
11
#848
01
#849
b0000000000111 '
11
#850
01
#851
b0000000001000 '
11
#852
01
#853
b0000000001001 '
11
#854
01
#855
b0000000001010 '
11
#856
01
#857
b0000000001011 '
11
#858
01
#859
b0000000001100 '
11
#860
01
#861
b0000000001101 '
11
#862
01
#863
b0000000001110 '
11
#864
01
#865
b0000000001111 '
11
#866
01
#867
1&
b0000000000000 '
11
#868
01
#869
0&
b0000000000001 '
b10000000 )
b110 *
b11000000 -
b00000010 .
11
#870
01
#871
b0000000000010 '
11
#872
01
#873
b0000000000011 '
11
#874
01
#875
b0000000000100 '
11
#876
01
#877
b0000000000101 '
11
#878
01
#879
b0000000000110 '
11
#880
01
#881
b0000000000111 '
11
#882
01
#883
b0000000001000 '
11
#884
01
#885
b0000000001001 '
11
#886
01
#887
b0000000001010 '
11
#888
01
#889
b0000000001011 '
11
#890
01
#891
b0000000001100 '
11
#892
01
#893
b0000000001101 '
11
#894
01
#895
b0000000001110 '
11
#896
01
#897
b0000000001111 '
11
#898
01
#899
1&
b0000000000000 '
11
#900
01
#901
0&
b0000000000001 '
b11000000 )
b101 *
b10000000 -
b00000011 .
11
#902
01
#903
b0000000000010 '
11
#904
01
#905
b0000000000011 '
11
#906
01
#907
b0000000000100 '
11
#908
01
#909
b0000000000101 '
11
#910
01
#911
b0000000000110 '
11
#912
01
#913
b0000000000111 '
11
#914
01
#915
b0000000001000 '
11
#916
01
#917
b0000000001001 '
11
#918
01
#919
b0000000001010 '
11
#920
01
#921
b0000000001011 '
11
#922
01
#923
b0000000001100 '
11
#924
01
#925
b0000000001101 '
11
#926
01
#927
b0000000001110 '
11
#928
01
#929
b0000000001111 '
11
#930
01
#931
1&
b0000000000000 '
11
#932
01
#933
0&
b0000000000001 '
b11100000 )
b100 *
b00000000 -
b00000100 .
11
#934
01
#935
b0000000000010 '
11
#936
01
#937
b0000000000011 '
11
#938
01
#939
b0000000000100 '
11
#940
01
#941
b0000000000101 '
11
#942
01
#943
b0000000000110 '
11
#944
01
#945
b0000000000111 '
11
#946
01
#947
b0000000001000 '
11
#948
01
#949
b0000000001001 '
11
#950
01
#951
b0000000001010 '
11
#952
01
#953
b0000000001011 '
11
#954
01
#955
b0000000001100 '
11
#956
01
#957
b0000000001101 '
11
#958
01
#959
b0000000001110 '
11
#960
01
#961
b0000000001111 '
11
#962
01
#963
1&
b0000000000000 '
11
#964
01
#965
0%
0&
b0000000000001 '
b11110000 )
b011 *
b00000101 .
11
#966
01
#967
b0000000000010 '
11
#968
01
#969
b0000000000011 '
11
#970
01
#971
b0000000000100 '
11
#972
01
#973
b0000000000101 '
11
#974
01
#975
b0000000000110 '
11
#976
01
#977
b0000000000111 '
11
#978
01
#979
b0000000001000 '
11
#980
01
#981
b0000000001001 '
11
#982
01
#983
b0000000001010 '
11
#984
01
#985
b0000000001011 '
11
#986
01
#987
b0000000001100 '
11
#988
01
#989
b0000000001101 '
11
#990
01
#991
b0000000001110 '
11
#992
01
#993
b0000000001111 '
11
#994
01
#995
1&
b0000000000000 '
11
#996
01
#997
0&
b0000000000001 '
b010 *
b00000110 .
11
#998
01
#999
b0000000000010 '
11
#1000
01
#1001
b0000000000011 '
11
#1002
01
#1003
b0000000000100 '
11
#1004
01
#1005
b0000000000101 '
11
#1006
01
#1007
b0000000000110 '
11
#1008
01
#1009
b0000000000111 '
11
#1010
01
#1011
b0000000001000 '
11
#1012
01
#1013
b0000000001001 '
11
#1014
01
#1015
b0000000001010 '
11
#1016
01
#1017
b0000000001011 '
11
#1018
01
#1019
b0000000001100 '
11
#1020
01
#1021
b0000000001101 '
11
#1022
01
#1023
b0000000001110 '
11
#1024
01
#1025
b0000000001111 '
11
#1026
01
#1027
1&
b0000000000000 '
11
#1028
01
#1029
0&
b0000000000001 '
b001 *
b00000111 .
11
#1030
01
#1031
b0000000000010 '
11
#1032
01
#1033
b0000000000011 '
11
#1034
01
#1035
b0000000000100 '
11
#1036
01
#1037
b0000000000101 '
11
#1038
01
#1039
b0000000000110 '
11
#1040
01
#1041
b0000000000111 '
11
#1042
01
#1043
b0000000001000 '
11
#1044
01
#1045
b0000000001001 '
11
#1046
01
#1047
b0000000001010 '
11
#1048
01
#1049
b0000000001011 '
11
#1050
01
#1051
b0000000001100 '
11
#1052
01
#1053
b0000000001101 '
11
#1054
01
#1055
b0000000001110 '
11
#1056
01
#1057
b0000000001111 '
11
#1058
01
#1059
1&
b0000000000000 '
11
#1060
01
#1061
0&
b0000000000001 '
b000 *
b00001000 .
11
#1062
01
#1063
b0000000000010 '
11
#1064
01
#1065
b0000000000011 '
11
#1066
01
#1067
b0000000000100 '
11
#1068
01
#1069
b0000000000101 '
11
#1070
01
#1071
b0000000000110 '
11
#1072
01
#1073
b0000000000111 '
11
#1074
01
#1075
b0000000001000 '
11
#1076
01
#1077
b0000000001001 '
11
#1078
01
#1079
b0000000001010 '
11
#1080
01
#1081
b0000000001011 '
11
#1082
01
#1083
b0000000001100 '
11
#1084
01
#1085
b0000000001101 '
11
#1086
01
#1087
b0000000001110 '
11
#1088
01
#1089
b0000000001111 '
11
#1090
01
#1091
1&
b0000000000000 '
11
#1092
01
#1093
0&
b0000000000001 '
b010 (
b00001001 .
b011 0
11
#1094
01
